gradio_pdf/__init__.py
gradio_pdf/pdf.py
gradio_pdf/pdf.pyi
gradio_pdf/templates/component/__vite-browser-external-DYxpcVy9.js
gradio_pdf/templates/component/index-BfdXe_BH.js
gradio_pdf/templates/component/index.js
gradio_pdf/templates/component/style.css
gradio_pdf/templates/example/__vite-browser-external-DYxpcVy9.js
gradio_pdf/templates/example/index-BfdXe_BH.js
gradio_pdf/templates/example/index.js
gradio_pdf/templates/example/style.css
gradio_pdf-0.0.20.dist-info/METADATA
gradio_pdf-0.0.20.dist-info/WHEEL
gradio_pdf-0.0.20.dist-info/licenses/LICENSE
gradio_pdf-0.0.20.dist-info/RECORD
