Metadata-Version: 2.3
Name: gradio_pdf
Version: 0.0.20
Summary: Easily display PDFs in Gradio
Project-URL: repository, https://github.com/freddyaboulton/gradio-pdf
Project-URL: space, https://huggingface.co/spaces/freddyaboulton/gradio_pdf
Author-email: Freddy Boulton <alfonsoboulton@gmail.com>
License: Apache-2.0
Keywords: Document QA,Documents,PDF,gradio,gradio custom component,gradio-template-Fallback
Classifier: Development Status :: 3 - Alpha
Classifier: License :: OSI Approved :: Apache Software License
Classifier: Operating System :: OS Independent
Classifier: Programming Language :: Python :: 3
Classifier: Programming Language :: Python :: 3 :: Only
Classifier: Programming Language :: Python :: 3.8
Classifier: Programming Language :: Python :: 3.9
Classifier: Programming Language :: Python :: 3.10
Classifier: Programming Language :: Python :: 3.11
Classifier: Topic :: Scientific/Engineering
Classifier: Topic :: Scientific/Engineering :: Artificial Intelligence
Classifier: Topic :: Scientific/Engineering :: Visualization
Requires-Python: >=3.8
Requires-Dist: gradio<6.0,>=4.0
Provides-Extra: dev
Requires-Dist: build; extra == 'dev'
Requires-Dist: twine; extra == 'dev'
